MANIFEST.in
setup.py
prpp/__init__.py
prpp.egg-info/PKG-INFO
prpp.egg-info/SOURCES.txt
prpp.egg-info/dependency_links.txt
prpp.egg-info/requires.txt
prpp.egg-info/top_level.txt
prpp/entities/__init__.py
prpp/entities/conferences.py
prpp/entities/devices.py
prpp/entities/reservations.py
prpp/entities/rooms.py
prpp/entities/users.py
prpp/entities/utils.py
prpp/stubs/__init__.py
prpp/stubs/plcm.py
prpp/stubs/plcmdevice.py
prpp/stubs/plcmerror.py
prpp/stubs/plcmreservation.py
prpp/stubs/plcmreservedparticipant.py
prpp/stubs/plcmreservedparticipantlist.py
prpp/stubs/plcmroom.py
prpp/wrapper/__init__.py
prpp/wrapper/request.py
prpp/wrapper/server.py