Metadata-Version: 1.1
Name: prpp
Version: 1.8.3
Summary: Python Polycom RealPresence Rest API wrapper
Home-page: http://www.sharingcloud.com/
Author: Adrien | SharingCloud
Author-email: sharingcloud-app@sharingcloud.com
License: UNKNOWN
Platform: UNKNOWN
Classifier: Development Status :: 5 - Production/Stable
Classifier: Topic :: System :: Networking
